onsset/__init__.py
onsset/ethiopia_runner.py
onsset/gui_runner.py
onsset/onsset.py
onsset/runner.py
onsset/specs.py
onsset-1.1a6.dist-info/LICENSE
onsset-1.1a6.dist-info/METADATA
onsset-1.1a6.dist-info/WHEEL
onsset-1.1a6.dist-info/top_level.txt
onsset-1.1a6.dist-info/RECORD
